note_client/__init__.py
note_client/note_client.py
NoteClient-0.2.1.dist-info/LICENSE
NoteClient-0.2.1.dist-info/METADATA
NoteClient-0.2.1.dist-info/WHEEL
NoteClient-0.2.1.dist-info/top_level.txt
NoteClient-0.2.1.dist-info/RECORD
