Metadata-Version: 2.1
Name: NoteClient
Version: 0.2.1
Summary: Automatically posts articles on note
Home-page: https://github.com/Mr-SuperInsane/NoteClient
Author: Nao Matsukami
Author-email: info@mr-insane.net
Classifier: Development Status :: 4 - Beta
Classifier: Intended Audience :: Developers
Classifier: Topic :: Software Development :: Build Tools
Classifier: License :: OSI Approved :: MIT License
Classifier: Programming Language :: Python :: 3
Classifier: Programming Language :: Python :: 3.7
Classifier: Programming Language :: Python :: 3.8
Classifier: Programming Language :: Python :: 3.9
License-File: LICENSE
Requires-Dist: selenium >=4.12.0
Requires-Dist: janome >=0.5.0
